{
   "System": "pPb",
   "Energy": "8.16 TeV",
   "Subject": "Hadron",
   "Observable": "v2{8}/v2{6}",
   "Dependency": "Ntrk",
   "Centrality": "Inclusive",
   "Record": "CMS 2020",
   "Selection": "PT = 0.3 - 3.0",
   "Comment": "",
   "HEPData": "https://www.hepdata.net/record/ins1731568",
   "X": [105.0,135.0,167.5,202.5,235.0,275.0,310.0],
   "EXLow": [15.0,15.0,17.5,17.5,15.0,25.0,10.0],
   "EXHigh": [15.0,15.0,17.5,17.5,15.0,25.0,10.0],
   "Y": [0.9895,0.9822,0.981,0.975,0.9574,0.9743,1.0074],
   "EYStatLow": [0.01066,0.01042,0.00767,0.0072,0.00809,0.0221,0.10907],
   "EYStatHigh": [0.01066,0.01042,0.00767,0.0072,0.00809,0.0221,0.10907],
   "EYSysLow": [0.02969,0.02947,0.02943,0.02925,0.02872,0.02923,0.03022],
   "EYSysHigh": [0.02969,0.02947,0.02943,0.02925,0.02872,0.02923,0.03022],
   "GlobalUncertainty": 0.0,
},
